neteval/L3_prediction.sh
neteval/Timer.py
neteval/__init__.py
neteval/alphafold_results.py
neteval/community_annotation.py
neteval/complex_evaluation.py
neteval/data_import_export_tools.py
neteval/edge_prediction.py
neteval/gene_mapper.py
neteval/gene_set_recovery_results.py
neteval/get_disgen_associations.py
neteval/get_gwas_associations.py
neteval/gsea_functions.py
neteval/net_to_csv.sh
neteval/netevalcmd.py
neteval/network_constructor.py
neteval/network_evaluation_functions.py
neteval/network_propagation.py
neteval/network_statistics.py
neteval/node_annotation.py
neteval/prepare_evaluation_data.py
neteval/process_data.py
neteval/processing_functions.py
neteval/query_ensembl.py
neteval/query_hgnc.py
neteval/query_uniprot.py
neteval/run_network_evaluation.py
neteval/shuffle_networks.py
neteval-0.2.2.data/scripts/L3_prediction.sh
neteval-0.2.2.data/scripts/alphafold_results.py
neteval-0.2.2.data/scripts/edge_prediction.py
neteval-0.2.2.data/scripts/get_disgen_associations.py
neteval-0.2.2.data/scripts/get_gwas_associations.py
neteval-0.2.2.data/scripts/netevalcmd.py
neteval-0.2.2.data/scripts/network_constructor.py
neteval-0.2.2.data/scripts/prepare_evaluation_data.py
neteval-0.2.2.data/scripts/process_data.py
neteval-0.2.2.data/scripts/run_network_evaluation.py
neteval-0.2.2.dist-info/AUTHORS.rst
neteval-0.2.2.dist-info/LICENSE
neteval-0.2.2.dist-info/METADATA
neteval-0.2.2.dist-info/WHEEL
neteval-0.2.2.dist-info/top_level.txt
neteval-0.2.2.dist-info/RECORD
