Metadata-Version: 2.1
Name: neteval
Version: 0.2.2
Summary: Package for standardization and evaluation of biological networks
Home-page: https://github.com/sarah-n-wright/Network_Evaluation_Tools
Author: Sarah Wright
Author-email: snwright@ucsd.edu
License: MIT license
Keywords: neteval,network,interaction,bioinformatics
Platform: UNKNOWN
Classifier: Development Status :: 2 - Pre-Alpha
Classifier: Intended Audience :: Developers
Classifier: License :: OSI Approved :: MIT License
Classifier: Natural Language :: English
Classifier: Programming Language :: Python :: 3.10
Classifier: Programming Language :: Python :: 3.11
Classifier: Programming Language :: Python :: 3.12
Requires-Python: >=3.10
License-File: LICENSE
License-File: AUTHORS.rst
Requires-Dist: argparse (>=1.4.0)
Requires-Dist: fuzzywuzzy (>=0.18.0)
Requires-Dist: goatools (>=1.3.1)
Requires-Dist: hidef (>=1.1.5)
Requires-Dist: httplib2 (>=0.20.2)
Requires-Dist: matplotlib (<3.7,>=3.5.0)
Requires-Dist: mygene (>=3.2.2)
Requires-Dist: ndex2 (>=3.5.0)
Requires-Dist: networkx (<3.0,>=2.6.3)
Requires-Dist: numpy (<2.0,>=1.21.4)
Requires-Dist: obonet (>=1.0.0)
Requires-Dist: pandas (<2.0,>=1.3.4)
Requires-Dist: requests (>=2.26.0)
Requires-Dist: scikit-learn (>=1.0.1)
Requires-Dist: scipy (>=1.7.2)
Requires-Dist: seaborn (>=0.13.0)
Requires-Dist: statsmodels (>=0.13.5)
Requires-Dist: tqdm (>=4.62.3)
